{"race":{"RaceName":"MCLwt2x    Men's Championship Lightweight 2x","RaceNumber":"289","Time":"18:19","EventDay":"Sunday","Round":"Final A","Stage":"F1","Progression":"","Status":"4","ShortName":"FA","RaceStarted":null,"NextRace":"0","Verdict":"","Event":"MCLwt2x","FullName":"Men's Championship Lightweight 2x","Trophy":"","Sponsor":null,"ResultStatus":"Official Result"},"lanes":[{"Lane":"1","CrewID":"233712","Split1":"01:37.5","Split2":"03:18.7","Split3":"05:00.9","Posn1":"","Posn2":"","Posn3":"","Finish":"06:46.56","Posn":"1","Status":"5","CrewNum":"238","CrewCode":"EDU","Event":"MCLwt2x","ClubName":"Edinburgh","CrewNames":"1 - D. Flockhart<br>2 - J. Temple","Blades":""},{"Lane":"2","CrewID":"233262","Split1":"01:38.2","Split2":"03:23.2","Split3":"05:10.0","Posn1":"","Posn2":"","Posn3":"","Finish":"06:57.80","Posn":"2","Status":"5","CrewNum":"240","CrewCode":"REA","Event":"MCLwt2x","ClubName":"Reading","CrewNames":"1 - S. O'Mahony<br>2 - F. Hamilton","Blades":""},{"Lane":"4","CrewID":"233414","Split1":"01:41.2","Split2":"03:28.1","Split3":"05:15.7","Posn1":"","Posn2":"","Posn3":"","Finish":"07:02.26","Posn":"3","Status":"5","CrewNum":"241","CrewCode":"OXB","Event":"MCLwt2x","ClubName":"Oxford Brookes Univ","CrewNames":"1 - B. Reeves<br>2 - O. Morgan","Blades":"0"},{"Lane":"3","CrewID":"233551","Split1":"01:41.0","Split2":"03:28.7","Split3":"05:17.3","Posn1":"","Posn2":"","Posn3":"","Finish":"07:03.94","Posn":"4","Status":"5","CrewNum":"239","CrewCode":"QUB","Event":"MCLwt2x","ClubName":"Queen's (Belfast)","CrewNames":"1 - M. Taylor<br>2 - H. Mahony","Blades":""},{"Lane":"6","CrewID":"232973","Split1":"01:42.8","Split2":"03:33.1","Split3":"05:26.4","Posn1":"","Posn2":"","Posn3":"","Finish":"07:22.88","Posn":"5","Status":"5","CrewNum":"244","CrewCode":"EXE","Event":"MCLwt2x","ClubName":"Exeter RC","CrewNames":"1 - S. Tyrie<br>2 - G. Rubino","Blades":"0"},{"Lane":"5","CrewID":"233367","Split1":"01:45.7","Split2":"03:38.3","Split3":"05:31.4","Posn1":"","Posn2":"","Posn3":"","Finish":"07:25.08","Posn":"6","Status":"5","CrewNum":"242","CrewCode":"BAT","Event":"MCLwt2x","ClubName":"Bath","CrewNames":"1 - J. Poat<br>2 - T. Bowles","Blades":""}]}