{"race":{"RaceName":"MInt8+    Men's Intermediate 8+","RaceNumber":"75","Time":"17:21","EventDay":"Saturday","Round":"Final C","Stage":"F3","Progression":"","Status":"4","ShortName":"FC","RaceStarted":null,"NextRace":"0","Verdict":"","Event":"MInt8+","FullName":"Men's Intermediate 8+","Trophy":"","Sponsor":null,"ResultStatus":"Official Result"},"lanes":[{"Lane":"3","CrewID":"233757","Split1":"01:33.8","Split2":"03:12.9","Split3":"04:54.2","Posn1":"","Posn2":"","Posn3":"","Finish":"06:33.08","Posn":"1","Status":"5","CrewNum":"362","CrewCode":"OXU (A)","Event":"MInt8+","ClubName":"Oxford","CrewNames":"1 - E. Baker<br>2 - B. Evans<br>3 - M. Ewenz<br>4 - W. Gasson<br>5 - K. Gibbons<br>6 - J. Smith<br>7 - G. Spill<br>8 - J. White<br>Cox - N. Cooke","Blades":""},{"Lane":"2","CrewID":"233149","Split1":"01:36.8","Split2":"03:15.4","Split3":"04:54.5","Posn1":"","Posn2":"","Posn3":"","Finish":"06:33.17","Posn":"2","Status":"5","CrewNum":"333","CrewCode":"QML","Event":"MInt8+","ClubName":"Queen Mary","CrewNames":"1 - C. Durbidge<br>2 - A. Flannery<br>3 - S. Habib<br>4 - B. Johnson<br>5 - S. Johnson<br>6 - J. Sanderson<br>7 - R. Wang<br>8 - B. Koetsier<br>Cox - R. Crispin","Blades":""},{"Lane":"4","CrewID":"232698","Split1":"01:36.6","Split2":"03:14.6","Split3":"04:55.5","Posn1":"","Posn2":"","Posn3":"","Finish":"06:33.28","Posn":"3","Status":"5","CrewNum":"351","CrewCode":"WAR (A)","Event":"MInt8+","ClubName":"Warwick","CrewNames":"1 - J. Breen<br>2 - J. Bedford<br>3 - A. Dawson<br>4 - O. Farmer<br>5 - C. McCaffery<br>6 - J. Semple<br>7 - T. Hall<br>8 - J. Hutchinson<br>Cox - D. Whitchurch","Blades":"0"},{"Lane":"6","CrewID":"232765","Split1":"01:38.6","Split2":"03:16.8","Split3":"04:57.0","Posn1":"","Posn2":"","Posn3":"","Finish":"06:38.74","Posn":"4","Status":"5","CrewNum":"363","CrewCode":"SWA","Event":"MInt8+","ClubName":"Swansea","CrewNames":"1 - G. Elder<br>2 - J. Gibson<br>3 - S. Carroll<br>4 - D. Carlson<br>5 - E. Mortlock<br>6 - C. Punter<br>7 - J. Foster<br>8 - T. Ross<br>Cox - F. Tomlin","Blades":""},{"Lane":"1","CrewID":"232847","Split1":"01:38.1","Split2":"03:18.1","Split3":"04:58.4","Posn1":"","Posn2":"","Posn3":"","Finish":"06:39.98","Posn":"5","Status":"5","CrewNum":"341","CrewCode":"SHF","Event":"MInt8+","ClubName":"Sheffield","CrewNames":"1 - J. Brown<br>2 - S. Armistead<br>3 - S. Colley<br>4 - R. Dawidek<br>5 - M. Farrow<br>6 - T. Walker<br>7 - J. Hugo<br>8 - M. Kilborn<br>Cox - Y. Patel","Blades":""},{"Lane":"5","CrewID":"233830","Split1":"01:39.2","Split2":"03:19.5","Split3":"05:00.6","Posn1":"","Posn2":"","Posn3":"","Finish":"06:40.53","Posn":"6","Status":"5","CrewNum":"334","CrewCode":"LEE","Event":"MInt8+","ClubName":"Leeds RC","CrewNames":"1 - M. Brigham<br>2 - M. Ashall<br>3 - J. Barnett<br>4 - J. Bradstock<br>5 - G. Brown<br>6 - J. Byrne<br>7 - B. Hansford<br>8 - F. Shah<br>Cox - H. Templeman","Blades":"0"}]}