{"race":{"RaceName":"MCLwt2-    Men's Championship Lightweight 2-","RaceNumber":"419","Time":"11:45","EventDay":"Monday","Round":"Rep  2","Stage":"R1","Progression":"1st 2 to Final","Status":"4","ShortName":"R 2","RaceStarted":null,"NextRace":"466","Verdict":"","Event":"MCLwt2-","FullName":"Men's Championship Lightweight 2-","Trophy":"","Sponsor":null,"ResultStatus":"Official Result"},"lanes":[{"Lane":"3","CrewID":"232972","Split1":"01:44.7","Split2":"03:33.8","Split3":"05:25.5","Posn1":"","Posn2":"","Posn3":"","Finish":"07:16.68","Posn":"1","Status":"5","CrewNum":"32","CrewCode":"EXE","Event":"MCLwt2-","ClubName":"Exeter RC","CrewNames":"1 - S. Tyrie<br>2 - L. Joost","Blades":"0"},{"Lane":"4","CrewID":"232752","Split1":"01:47.7","Split2":"03:35.8","Split3":"05:26.1","Posn1":"","Posn2":"","Posn3":"","Finish":"07:18.37","Posn":"2","Status":"5","CrewNum":"30","CrewCode":"NEW (B)","Event":"MCLwt2-","ClubName":"Newcastle Univ","CrewNames":"1 - S. Baker<br>2 - H. Storey","Blades":"0"},{"Lane":"5","CrewID":"233369","Split1":"01:50.2","Split2":"03:40.5","Split3":"05:30.3","Posn1":"","Posn2":"","Posn3":"","Finish":"07:20.23","Posn":"3","Status":"5","CrewNum":"33","CrewCode":"BAT","Event":"MCLwt2-","ClubName":"Bath","CrewNames":"1 - J. Sadler<br>2 - J. Laurenson","Blades":""},{"Lane":"2","CrewID":"233328","Split1":"01:48.6","Split2":"03:39.3","Split3":"05:30.1","Posn1":"","Posn2":"","Posn3":"","Finish":"07:22.12","Posn":"4","Status":"5","CrewNum":"26","CrewCode":"OXU (B)","Event":"MCLwt2-","ClubName":"Oxford","CrewNames":"1 - A. Rowe-Jones<br>2 - A. Crumpton","Blades":""}]}